{
  "time_range": {
    "start": "2026-06-27T08:04:36.103634426-04:00",
    "end": "2026-06-27T20:04:36.103634426-04:00"
  },
  "showtimes": [
    {
      "show_time": "2026-06-27T09:00:00",
      "movie": "The Invite",
      "theater": "Downtown Brooklyn",
      "cinema_id": "2101",
      "session_id": "131950",
      "presentation_slug": "the-invite",
      "open_caption": false
    },
    {
      "show_time": "2026-06-27T09:15:00",
      "movie": "Supergirl (2026)",
      "theater": "Downtown Brooklyn",
      "cinema_id": "2101",
      "session_id": "132415",
      "presentation_slug": "supergirl-2026",
      "open_caption": false
    },
    {
      "show_time": "2026-06-27T09:30:00",
      "movie": "Maddie's Secret",
      "theater": "Downtown Brooklyn",
      "cinema_id": "2101",
      "session_id": "132014",
      "presentation_slug": "maddies-secret",
      "open_caption": false
    },
    {
      "show_time": "2026-06-27T10:00:00",
      "movie": "Toy Story 5",
      "theater": "Downtown Brooklyn",
      "cinema_id": "2101",
      "session_id": "132416",
      "presentation_slug": "hdr-by-barco-toy-story-5",
      "open_caption": false
    },
    {
      "show_time": "2026-06-27T10:00:00",
      "movie": "The Death of Robin Hood",
      "theater": "Downtown Brooklyn",
      "cinema_id": "2101",
      "session_id": "132642",
      "presentation_slug": "the-death-of-robin-hood",
      "open_caption": false
    },
    {
      "show_time": "2026-06-27T10:15:00",
      "movie": "Godzilla vs. Biollante",
      "theater": "Downtown Brooklyn",
      "cinema_id": "2101",
      "session_id": "132460",
      "presentation_slug": "godzilla-vs-biollante",
      "open_caption": false
    },
    {
      "show_time": "2026-06-27T10:15:00",
      "movie": "Leviticus",
      "theater": "Downtown Brooklyn",
      "cinema_id": "2101",
      "session_id": "132636",
      "presentation_slug": "leviticus",
      "open_caption": false
    },
    {
      "show_time": "2026-06-27T10:30:00",
      "movie": "Disclosure Day",
      "theater": "Downtown Brooklyn",
      "cinema_id": "2101",
      "session_id": "132644",
      "presentation_slug": "disclosure-day",
      "open_caption": false
    },
    {
      "show_time": "2026-06-27T10:45:00",
      "movie": "The Invite",
      "theater": "Downtown Brooklyn",
      "cinema_id": "2101",
      "session_id": "131945",
      "presentation_slug": "the-invite",
      "open_caption": false
    },
    {
      "show_time": "2026-06-27T11:00:00",
      "movie": "Disclosure Day",
      "theater": "Lower Manhattan",
      "cinema_id": "2103",
      "session_id": "92345",
      "presentation_slug": "disclosure-day",
      "open_caption": false
    },
    {
      "show_time": "2026-06-27T11:00:00",
      "movie": "jackass: best and last",
      "theater": "Downtown Brooklyn",
      "cinema_id": "2101",
      "session_id": "132469",
      "presentation_slug": "jackass-best-and-last",
      "open_caption": false
    },
    {
      "show_time": "2026-06-27T11:00:00",
      "movie": "Stop! That! Train!",
      "theater": "Lower Manhattan",
      "cinema_id": "2103",
      "session_id": "92359",
      "presentation_slug": "stop-that-train",
      "open_caption": false
    },
    {
      "show_time": "2026-06-27T11:15:00",
      "movie": "Girls Like Girls",
      "theater": "Downtown Brooklyn",
      "cinema_id": "2101",
      "session_id": "132632",
      "presentation_slug": "girls-like-girls",
      "open_caption": false
    },
    {
      "show_time": "2026-06-27T11:15:00",
      "movie": "Obsession (2026)",
      "theater": "Lower Manhattan",
      "cinema_id": "2103",
      "session_id": "92335",
      "presentation_slug": "obsession-2026",
      "open_caption": true
    },
    {
      "show_time": "2026-06-27T11:15:00",
      "movie": "Obsession (2026)",
      "theater": "Downtown Brooklyn",
      "cinema_id": "2101",
      "session_id": "132651",
      "presentation_slug": "obsession-2026",
      "open_caption": false
    },
    {
      "show_time": "2026-06-27T11:15:00",
      "movie": "Toy Story 5",
      "theater": "Lower Manhattan",
      "cinema_id": "2103",
      "session_id": "92317",
      "presentation_slug": "toy-story-5",
      "open_caption": false
    },
    {
      "show_time": "2026-06-27T11:30:00",
      "movie": "Backrooms",
      "theater": "Lower Manhattan",
      "cinema_id": "2103",
      "session_id": "92356",
      "presentation_slug": "backrooms",
      "open_caption": false
    },
    {
      "show_time": "2026-06-27T11:30:00",
      "movie": "Godzilla vs. Biollante",
      "theater": "Lower Manhattan",
      "cinema_id": "2103",
      "session_id": "92152",
      "presentation_slug": "godzilla-vs-biollante",
      "open_caption": false
    },
    {
      "show_time": "2026-06-27T11:30:00",
      "movie": "Leviticus",
      "theater": "Lower Manhattan",
      "cinema_id": "2103",
      "session_id": "92340",
      "presentation_slug": "leviticus",
      "open_caption": false
    },
    {
      "show_time": "2026-06-27T11:45:00",
      "movie": "Toy Story 5",
      "theater": "Lower Manhattan",
      "cinema_id": "2103",
      "session_id": "92327",
      "presentation_slug": "toy-story-5",
      "open_caption": false
    },
    {
      "show_time": "2026-06-27T12:00:00",
      "movie": "Supergirl (2026)",
      "theater": "Lower Manhattan",
      "cinema_id": "2103",
      "session_id": "90838",
      "presentation_slug": "supergirl-2026",
      "open_caption": false
    },
    {
      "show_time": "2026-06-27T12:00:00",
      "movie": "The Death of Robin Hood",
      "theater": "Lower Manhattan",
      "cinema_id": "2103",
      "session_id": "92352",
      "presentation_slug": "the-death-of-robin-hood",
      "open_caption": false
    },
    {
      "show_time": "2026-06-27T12:00:00",
      "movie": "The Invite",
      "theater": "Downtown Brooklyn",
      "cinema_id": "2101",
      "session_id": "131951",
      "presentation_slug": "the-invite",
      "open_caption": false
    },
    {
      "show_time": "2026-06-27T12:15:00",
      "movie": "Supergirl (2026)",
      "theater": "Downtown Brooklyn",
      "cinema_id": "2101",
      "session_id": "132414",
      "presentation_slug": "supergirl-2026",
      "open_caption": false
    },
    {
      "show_time": "2026-06-27T12:30:00",
      "movie": "Girls Like Girls",
      "theater": "Lower Manhattan",
      "cinema_id": "2103",
      "session_id": "92336",
      "presentation_slug": "girls-like-girls",
      "open_caption": false
    },
    {
      "show_time": "2026-06-27T12:30:00",
      "movie": "Maddie's Secret",
      "theater": "Downtown Brooklyn",
      "cinema_id": "2101",
      "session_id": "132013",
      "presentation_slug": "maddies-secret",
      "open_caption": false
    },
    {
      "show_time": "2026-06-27T13:00:00",
      "movie": "Toy Story 5",
      "theater": "Downtown Brooklyn",
      "cinema_id": "2101",
      "session_id": "132417",
      "presentation_slug": "hdr-by-barco-toy-story-5",
      "open_caption": false
    },
    {
      "show_time": "2026-06-27T13:00:00",
      "movie": "jackass: best and last",
      "theater": "Lower Manhattan",
      "cinema_id": "2103",
      "session_id": "91377",
      "presentation_slug": "jackass-best-and-last",
      "open_caption": false
    },
    {
      "show_time": "2026-06-27T13:00:00",
      "movie": "Leviticus",
      "theater": "Downtown Brooklyn",
      "cinema_id": "2101",
      "session_id": "132637",
      "presentation_slug": "leviticus",
      "open_caption": false
    },
    {
      "show_time": "2026-06-27T13:00:00",
      "movie": "Toy Story 5",
      "theater": "Lower Manhattan",
      "cinema_id": "2103",
      "session_id": "92319",
      "presentation_slug": "toy-story-5",
      "open_caption": false
    },
    {
      "show_time": "2026-06-27T13:15:00",
      "movie": "Blow Out",
      "theater": "Downtown Brooklyn",
      "cinema_id": "2101",
      "session_id": "132461",
      "presentation_slug": "blow-out",
      "open_caption": false
    },
    {
      "show_time": "2026-06-27T13:15:00",
      "movie": "Supergirl (2026)",
      "theater": "Lower Manhattan",
      "cinema_id": "2103",
      "session_id": "92326",
      "presentation_slug": "supergirl-2026",
      "open_caption": false
    },
    {
      "show_time": "2026-06-27T13:30:00",
      "movie": "Scary Movie (2026)",
      "theater": "Downtown Brooklyn",
      "cinema_id": "2101",
      "session_id": "132648",
      "presentation_slug": "scary-movie-2026",
      "open_caption": false
    },
    {
      "show_time": "2026-06-27T13:45:00",
      "movie": "jackass: best and last",
      "theater": "Downtown Brooklyn",
      "cinema_id": "2101",
      "session_id": "132470",
      "presentation_slug": "jackass-best-and-last",
      "open_caption": false
    },
    {
      "show_time": "2026-06-27T13:45:00",
      "movie": "Scary Movie (2026)",
      "theater": "Lower Manhattan",
      "cinema_id": "2103",
      "session_id": "92349",
      "presentation_slug": "scary-movie-2026",
      "open_caption": false
    },
    {
      "show_time": "2026-06-27T13:45:00",
      "movie": "The Invite",
      "theater": "Downtown Brooklyn",
      "cinema_id": "2101",
      "session_id": "131946",
      "presentation_slug": "the-invite",
      "open_caption": true
    },
    {
      "show_time": "2026-06-27T14:00:00",
      "movie": "Girls Like Girls",
      "theater": "Downtown Brooklyn",
      "cinema_id": "2101",
      "session_id": "132631",
      "presentation_slug": "girls-like-girls",
      "open_caption": true
    },
    {
      "show_time": "2026-06-27T14:15:00",
      "movie": "Disclosure Day",
      "theater": "Downtown Brooklyn",
      "cinema_id": "2101",
      "session_id": "132645",
      "presentation_slug": "disclosure-day",
      "open_caption": true
    },
    {
      "show_time": "2026-06-27T14:15:00",
      "movie": "Leviticus",
      "theater": "Lower Manhattan",
      "cinema_id": "2103",
      "session_id": "92341",
      "presentation_slug": "leviticus",
      "open_caption": false
    },
    {
      "show_time": "2026-06-27T14:15:00",
      "movie": "Obsession (2026)",
      "theater": "Lower Manhattan",
      "cinema_id": "2103",
      "session_id": "92334",
      "presentation_slug": "obsession-2026",
      "open_caption": false
    },
    {
      "show_time": "2026-06-27T14:15:00",
      "movie": "Toy Story 5",
      "theater": "Lower Manhattan",
      "cinema_id": "2103",
      "session_id": "92316",
      "presentation_slug": "toy-story-5",
      "open_caption": false
    },
    {
      "show_time": "2026-06-27T14:30:00",
      "movie": "Blow Out",
      "theater": "Lower Manhattan",
      "cinema_id": "2103",
      "session_id": "92157",
      "presentation_slug": "blow-out",
      "open_caption": false
    },
    {
      "show_time": "2026-06-27T14:30:00",
      "movie": "Disclosure Day",
      "theater": "Lower Manhattan",
      "cinema_id": "2103",
      "session_id": "92346",
      "presentation_slug": "disclosure-day",
      "open_caption": true
    },
    {
      "show_time": "2026-06-27T14:30:00",
      "movie": "Obsession (2026)",
      "theater": "Downtown Brooklyn",
      "cinema_id": "2101",
      "session_id": "132650",
      "presentation_slug": "obsession-2026",
      "open_caption": false
    },
    {
      "show_time": "2026-06-27T14:45:00",
      "movie": "Backrooms",
      "theater": "Lower Manhattan",
      "cinema_id": "2103",
      "session_id": "92357",
      "presentation_slug": "backrooms",
      "open_caption": false
    },
    {
      "show_time": "2026-06-27T14:45:00",
      "movie": "Toy Story 5",
      "theater": "Lower Manhattan",
      "cinema_id": "2103",
      "session_id": "92330",
      "presentation_slug": "toy-story-5",
      "open_caption": false
    },
    {
      "show_time": "2026-06-27T15:00:00",
      "movie": "Supergirl (2026)",
      "theater": "Lower Manhattan",
      "cinema_id": "2103",
      "session_id": "90839",
      "presentation_slug": "supergirl-2026",
      "open_caption": false
    },
    {
      "show_time": "2026-06-27T15:00:00",
      "movie": "The Invite",
      "theater": "Downtown Brooklyn",
      "cinema_id": "2101",
      "session_id": "131952",
      "presentation_slug": "the-invite",
      "open_caption": false
    },
    {
      "show_time": "2026-06-27T15:15:00",
      "movie": "The Death of Robin Hood",
      "theater": "Lower Manhattan",
      "cinema_id": "2103",
      "session_id": "92353",
      "presentation_slug": "the-death-of-robin-hood",
      "open_caption": true
    },
    {
      "show_time": "2026-06-27T15:30:00",
      "movie": "Girls Like Girls",
      "theater": "Lower Manhattan",
      "cinema_id": "2103",
      "session_id": "92337",
      "presentation_slug": "girls-like-girls",
      "open_caption": false
    },
    {
      "show_time": "2026-06-27T15:30:00",
      "movie": "Maddie's Secret",
      "theater": "Downtown Brooklyn",
      "cinema_id": "2101",
      "session_id": "132012",
      "presentation_slug": "maddies-secret",
      "open_caption": false
    },
    {
      "show_time": "2026-06-27T15:30:00",
      "movie": "Supergirl (2026)",
      "theater": "Downtown Brooklyn",
      "cinema_id": "2101",
      "session_id": "132413",
      "presentation_slug": "supergirl-2026",
      "open_caption": true
    },
    {
      "show_time": "2026-06-27T15:45:00",
      "movie": "jackass: best and last",
      "theater": "Lower Manhattan",
      "cinema_id": "2103",
      "session_id": "91378",
      "presentation_slug": "jackass-best-and-last",
      "open_caption": false
    },
    {
      "show_time": "2026-06-27T15:45:00",
      "movie": "Leviticus",
      "theater": "Downtown Brooklyn",
      "cinema_id": "2101",
      "session_id": "132635",
      "presentation_slug": "leviticus",
      "open_caption": false
    },
    {
      "show_time": "2026-06-27T16:00:00",
      "movie": "Toy Story 5",
      "theater": "Downtown Brooklyn",
      "cinema_id": "2101",
      "session_id": "132418",
      "presentation_slug": "hdr-by-barco-toy-story-5",
      "open_caption": false
    },
    {
      "show_time": "2026-06-27T16:00:00",
      "movie": "Toy Story 5",
      "theater": "Lower Manhattan",
      "cinema_id": "2103",
      "session_id": "92321",
      "presentation_slug": "toy-story-5",
      "open_caption": false
    },
    {
      "show_time": "2026-06-27T16:15:00",
      "movie": "Obsession (2026)",
      "theater": "Downtown Brooklyn",
      "cinema_id": "2101",
      "session_id": "132649",
      "presentation_slug": "obsession-2026",
      "open_caption": false
    },
    {
      "show_time": "2026-06-27T16:15:00",
      "movie": "Supergirl (2026)",
      "theater": "Lower Manhattan",
      "cinema_id": "2103",
      "session_id": "92323",
      "presentation_slug": "supergirl-2026",
      "open_caption": false
    },
    {
      "show_time": "2026-06-27T16:30:00",
      "movie": "jackass: best and last",
      "theater": "Downtown Brooklyn",
      "cinema_id": "2101",
      "session_id": "132471",
      "presentation_slug": "jackass-best-and-last",
      "open_caption": false
    },
    {
      "show_time": "2026-06-27T16:30:00",
      "movie": "Scary Movie (2026)",
      "theater": "Downtown Brooklyn",
      "cinema_id": "2101",
      "session_id": "132640",
      "presentation_slug": "scary-movie-2026",
      "open_caption": false
    },
    {
      "show_time": "2026-06-27T16:45:00",
      "movie": "Girls Like Girls",
      "theater": "Downtown Brooklyn",
      "cinema_id": "2101",
      "session_id": "132630",
      "presentation_slug": "girls-like-girls",
      "open_caption": false
    },
    {
      "show_time": "2026-06-27T16:45:00",
      "movie": "Stop! That! Train!",
      "theater": "Lower Manhattan",
      "cinema_id": "2103",
      "session_id": "92360",
      "presentation_slug": "stop-that-train",
      "open_caption": false
    },
    {
      "show_time": "2026-06-27T16:45:00",
      "movie": "The Invite",
      "theater": "Downtown Brooklyn",
      "cinema_id": "2101",
      "session_id": "131947",
      "presentation_slug": "the-invite",
      "open_caption": false
    },
    {
      "show_time": "2026-06-27T17:00:00",
      "movie": "Leviticus",
      "theater": "Lower Manhattan",
      "cinema_id": "2103",
      "session_id": "92342",
      "presentation_slug": "leviticus",
      "open_caption": false
    },
    {
      "show_time": "2026-06-27T17:15:00",
      "movie": "Obsession (2026)",
      "theater": "Lower Manhattan",
      "cinema_id": "2103",
      "session_id": "92332",
      "presentation_slug": "obsession-2026",
      "open_caption": false
    },
    {
      "show_time": "2026-06-27T17:15:00",
      "movie": "Supergirl (2026)",
      "theater": "Lower Manhattan",
      "cinema_id": "2103",
      "session_id": "92315",
      "presentation_slug": "supergirl-2026",
      "open_caption": false
    },
    {
      "show_time": "2026-06-27T17:45:00",
      "movie": "Supergirl (2026)",
      "theater": "Lower Manhattan",
      "cinema_id": "2103",
      "session_id": "92404",
      "presentation_slug": "supergirl-2026",
      "open_caption": false
    },
    {
      "show_time": "2026-06-27T17:45:00",
      "movie": "Toy Story 5",
      "theater": "Lower Manhattan",
      "cinema_id": "2103",
      "session_id": "92329",
      "presentation_slug": "toy-story-5",
      "open_caption": false
    },
    {
      "show_time": "2026-06-27T18:00:00",
      "movie": "Backrooms",
      "theater": "Lower Manhattan",
      "cinema_id": "2103",
      "session_id": "92339",
      "presentation_slug": "backrooms",
      "open_caption": true
    },
    {
      "show_time": "2026-06-27T18:00:00",
      "movie": "Disclosure Day",
      "theater": "Downtown Brooklyn",
      "cinema_id": "2101",
      "session_id": "132647",
      "presentation_slug": "disclosure-day",
      "open_caption": false
    },
    {
      "show_time": "2026-06-27T18:00:00",
      "movie": "Supergirl (2026)",
      "theater": "Lower Manhattan",
      "cinema_id": "2103",
      "session_id": "90840",
      "presentation_slug": "supergirl-2026",
      "open_caption": false
    },
    {
      "show_time": "2026-06-27T18:00:00",
      "movie": "The Invite",
      "theater": "Downtown Brooklyn",
      "cinema_id": "2101",
      "session_id": "131953",
      "presentation_slug": "the-invite",
      "open_caption": false
    },
    {
      "show_time": "2026-06-27T18:15:00",
      "movie": "Disclosure Day",
      "theater": "Lower Manhattan",
      "cinema_id": "2103",
      "session_id": "92348",
      "presentation_slug": "disclosure-day",
      "open_caption": false
    },
    {
      "show_time": "2026-06-27T18:30:00",
      "movie": "Girls Like Girls",
      "theater": "Lower Manhattan",
      "cinema_id": "2103",
      "session_id": "92338",
      "presentation_slug": "girls-like-girls",
      "open_caption": false
    },
    {
      "show_time": "2026-06-27T18:30:00",
      "movie": "jackass: best and last",
      "theater": "Lower Manhattan",
      "cinema_id": "2103",
      "session_id": "91379",
      "presentation_slug": "jackass-best-and-last",
      "open_caption": false
    },
    {
      "show_time": "2026-06-27T18:30:00",
      "movie": "Maddie's Secret",
      "theater": "Downtown Brooklyn",
      "cinema_id": "2101",
      "session_id": "132011",
      "presentation_slug": "maddies-secret",
      "open_caption": false
    },
    {
      "show_time": "2026-06-27T18:30:00",
      "movie": "The Death of Robin Hood",
      "theater": "Lower Manhattan",
      "cinema_id": "2103",
      "session_id": "92355",
      "presentation_slug": "the-death-of-robin-hood",
      "open_caption": false
    },
    {
      "show_time": "2026-06-27T18:30:00",
      "movie": "Toy Story 5",
      "theater": "Downtown Brooklyn",
      "cinema_id": "2101",
      "session_id": "132412",
      "presentation_slug": "toy-story-5",
      "open_caption": false
    },
    {
      "show_time": "2026-06-27T18:45:00",
      "movie": "Leviticus",
      "theater": "Downtown Brooklyn",
      "cinema_id": "2101",
      "session_id": "132634",
      "presentation_slug": "leviticus",
      "open_caption": false
    },
    {
      "show_time": "2026-06-27T19:00:00",
      "movie": "Supergirl (2026)",
      "theater": "Downtown Brooklyn",
      "cinema_id": "2101",
      "session_id": "131029",
      "presentation_slug": "hdr-by-barco-supergirl-2026",
      "open_caption": false
    },
    {
      "show_time": "2026-06-27T19:00:00",
      "movie": "Toy Story 5",
      "theater": "Lower Manhattan",
      "cinema_id": "2103",
      "session_id": "92320",
      "presentation_slug": "toy-story-5",
      "open_caption": false
    },
    {
      "show_time": "2026-06-27T19:15:00",
      "movie": "jackass: best and last",
      "theater": "Downtown Brooklyn",
      "cinema_id": "2101",
      "session_id": "132473",
      "presentation_slug": "jackass-best-and-last",
      "open_caption": false
    },
    {
      "show_time": "2026-06-27T19:15:00",
      "movie": "Supergirl (2026)",
      "theater": "Lower Manhattan",
      "cinema_id": "2103",
      "session_id": "92324",
      "presentation_slug": "supergirl-2026",
      "open_caption": false
    },
    {
      "show_time": "2026-06-27T19:15:00",
      "movie": "The Invite",
      "theater": "Downtown Brooklyn",
      "cinema_id": "2101",
      "session_id": "132737",
      "presentation_slug": "the-invite",
      "open_caption": false
    },
    {
      "show_time": "2026-06-27T19:30:00",
      "movie": "Obsession (2026)",
      "theater": "Downtown Brooklyn",
      "cinema_id": "2101",
      "session_id": "132736",
      "presentation_slug": "obsession-2026",
      "open_caption": false
    },
    {
      "show_time": "2026-06-27T19:30:00",
      "movie": "Stop! That! Train!",
      "theater": "Downtown Brooklyn",
      "cinema_id": "2101",
      "session_id": "132639",
      "presentation_slug": "stop-that-train",
      "open_caption": false
    },
    {
      "show_time": "2026-06-27T19:45:00",
      "movie": "Leviticus",
      "theater": "Lower Manhattan",
      "cinema_id": "2103",
      "session_id": "92344",
      "presentation_slug": "leviticus",
      "open_caption": false
    },
    {
      "show_time": "2026-06-27T19:45:00",
      "movie": "Scary Movie (2026)",
      "theater": "Lower Manhattan",
      "cinema_id": "2103",
      "session_id": "92350",
      "presentation_slug": "scary-movie-2026",
      "open_caption": false
    },
    {
      "show_time": "2026-06-27T19:45:00",
      "movie": "The Invite",
      "theater": "Downtown Brooklyn",
      "cinema_id": "2101",
      "session_id": "131948",
      "presentation_slug": "the-invite",
      "open_caption": false
    }
  ]
}
