{
  "time_range": {
    "start": "2025-12-07T06:08:43.715491957-05:00",
    "end": "2025-12-07T18:08:43.715491957-05:00"
  },
  "showtimes": [
    {
      "show_time": "2025-12-07T09:00:00",
      "movie": "Wicked: For Good",
      "theater": "Downtown Brooklyn",
      "cinema_id": "2101",
      "session_id": "119809",
      "presentation_slug": "wicked-for-good",
      "open_caption": false
    },
    {
      "show_time": "2025-12-07T09:00:00",
      "movie": "Zootopia 2",
      "theater": "Downtown Brooklyn",
      "cinema_id": "2101",
      "session_id": "119783",
      "presentation_slug": "zootopia-2",
      "open_caption": false
    },
    {
      "show_time": "2025-12-07T09:15:00",
      "movie": "Now You See Me: Now You Don't",
      "theater": "Downtown Brooklyn",
      "cinema_id": "2101",
      "session_id": "119807",
      "presentation_slug": "now-you-see-me-now-you-dont",
      "open_caption": false
    },
    {
      "show_time": "2025-12-07T09:15:00",
      "movie": "Zootopia 2",
      "theater": "Downtown Brooklyn",
      "cinema_id": "2101",
      "session_id": "119786",
      "presentation_slug": "zootopia-2",
      "open_caption": false
    },
    {
      "show_time": "2025-12-07T09:30:00",
      "movie": "Hamnet",
      "theater": "Downtown Brooklyn",
      "cinema_id": "2101",
      "session_id": "119803",
      "presentation_slug": "hamnet",
      "open_caption": false
    },
    {
      "show_time": "2025-12-07T10:00:00",
      "movie": "Eternity",
      "theater": "Downtown Brooklyn",
      "cinema_id": "2101",
      "session_id": "119820",
      "presentation_slug": "eternity",
      "open_caption": true
    },
    {
      "show_time": "2025-12-07T10:00:00",
      "movie": "Jujutsu Kaisen: Execution (Dubbed)",
      "theater": "Downtown Brooklyn",
      "cinema_id": "2101",
      "session_id": "118698",
      "presentation_slug": "jujutsu-kaisen-execution-dubbed",
      "open_caption": false
    },
    {
      "show_time": "2025-12-07T10:15:00",
      "movie": "Five Nights at Freddy's 2",
      "theater": "Downtown Brooklyn",
      "cinema_id": "2101",
      "session_id": "118051",
      "presentation_slug": "five-nights-at-freddys-2",
      "open_caption": false
    },
    {
      "show_time": "2025-12-07T10:30:00",
      "movie": "Eternity",
      "theater": "Lower Manhattan",
      "cinema_id": "2103",
      "session_id": "81321",
      "presentation_slug": "eternity",
      "open_caption": false
    },
    {
      "show_time": "2025-12-07T10:30:00",
      "movie": "Five Nights at Freddy's 2",
      "theater": "Lower Manhattan",
      "cinema_id": "2103",
      "session_id": "79448",
      "presentation_slug": "five-nights-at-freddys-2",
      "open_caption": false
    },
    {
      "show_time": "2025-12-07T10:30:00",
      "movie": "Rental Family",
      "theater": "Downtown Brooklyn",
      "cinema_id": "2101",
      "session_id": "119815",
      "presentation_slug": "rental-family",
      "open_caption": false
    },
    {
      "show_time": "2025-12-07T10:45:00",
      "movie": "Wake Up Dead Man: A Knives Out Mystery",
      "theater": "Lower Manhattan",
      "cinema_id": "2103",
      "session_id": "81334",
      "presentation_slug": "wake-up-dead-man-a-knives-out-mystery",
      "open_caption": false
    },
    {
      "show_time": "2025-12-07T10:45:00",
      "movie": "Wake Up Dead Man: A Knives Out Mystery",
      "theater": "Downtown Brooklyn",
      "cinema_id": "2101",
      "session_id": "119791",
      "presentation_slug": "wake-up-dead-man-a-knives-out-mystery",
      "open_caption": false
    },
    {
      "show_time": "2025-12-07T11:00:00",
      "movie": "Jujutsu Kaisen: Execution (Dubbed)",
      "theater": "Lower Manhattan",
      "cinema_id": "2103",
      "session_id": "79822",
      "presentation_slug": "jujutsu-kaisen-execution-dubbed",
      "open_caption": false
    },
    {
      "show_time": "2025-12-07T11:00:00",
      "movie": "THE HOLIDAY",
      "theater": "Downtown Brooklyn",
      "cinema_id": "2101",
      "session_id": "118103",
      "presentation_slug": "the-holiday",
      "open_caption": false
    },
    {
      "show_time": "2025-12-07T11:00:00",
      "movie": "Wicked: For Good",
      "theater": "Downtown Brooklyn",
      "cinema_id": "2101",
      "session_id": "119795",
      "presentation_slug": "wicked-for-good",
      "open_caption": false
    },
    {
      "show_time": "2025-12-07T11:10:00",
      "movie": "THE HOLIDAY",
      "theater": "Lower Manhattan",
      "cinema_id": "2103",
      "session_id": "79395",
      "presentation_slug": "the-holiday",
      "open_caption": false
    },
    {
      "show_time": "2025-12-07T11:15:00",
      "movie": "Rental Family",
      "theater": "Lower Manhattan",
      "cinema_id": "2103",
      "session_id": "81326",
      "presentation_slug": "rental-family",
      "open_caption": false
    },
    {
      "show_time": "2025-12-07T11:15:00",
      "movie": "Wicked: For Good",
      "theater": "Lower Manhattan",
      "cinema_id": "2103",
      "session_id": "81338",
      "presentation_slug": "wicked-for-good",
      "open_caption": false
    },
    {
      "show_time": "2025-12-07T11:50:00",
      "movie": "Zootopia 2",
      "theater": "Lower Manhattan",
      "cinema_id": "2103",
      "session_id": "81330",
      "presentation_slug": "zootopia-2",
      "open_caption": false
    },
    {
      "show_time": "2025-12-07T11:55:00",
      "movie": "Kill Bill: The Whole Bloody Affair",
      "theater": "Lower Manhattan",
      "cinema_id": "2103",
      "session_id": "81482",
      "presentation_slug": "kill-bill-the-whole-bloody-affair",
      "open_caption": false
    },
    {
      "show_time": "2025-12-07T12:00:00",
      "movie": "Elf",
      "theater": "Lower Manhattan",
      "cinema_id": "2103",
      "session_id": "79313",
      "presentation_slug": "movie-party-elf",
      "open_caption": false
    },
    {
      "show_time": "2025-12-07T12:00:00",
      "movie": "Sentimental Value",
      "theater": "Downtown Brooklyn",
      "cinema_id": "2101",
      "session_id": "119782",
      "presentation_slug": "sentimental-value",
      "open_caption": true
    },
    {
      "show_time": "2025-12-07T12:00:00",
      "movie": "Suburban Fury",
      "theater": "Lower Manhattan",
      "cinema_id": "2103",
      "session_id": "80144",
      "presentation_slug": "suburban-fury",
      "open_caption": false
    },
    {
      "show_time": "2025-12-07T12:05:00",
      "movie": "Hamnet",
      "theater": "Lower Manhattan",
      "cinema_id": "2103",
      "session_id": "81317",
      "presentation_slug": "hamnet",
      "open_caption": false
    },
    {
      "show_time": "2025-12-07T12:15:00",
      "movie": "Zootopia 2",
      "theater": "Downtown Brooklyn",
      "cinema_id": "2101",
      "session_id": "119787",
      "presentation_slug": "zootopia-2",
      "open_caption": true
    },
    {
      "show_time": "2025-12-07T12:30:00",
      "movie": "Now You See Me: Now You Don't",
      "theater": "Downtown Brooklyn",
      "cinema_id": "2101",
      "session_id": "119808",
      "presentation_slug": "now-you-see-me-now-you-dont",
      "open_caption": false
    },
    {
      "show_time": "2025-12-07T12:30:00",
      "movie": "Wake Up Dead Man: A Knives Out Mystery",
      "theater": "Downtown Brooklyn",
      "cinema_id": "2101",
      "session_id": "119812",
      "presentation_slug": "wake-up-dead-man-a-knives-out-mystery",
      "open_caption": false
    },
    {
      "show_time": "2025-12-07T12:45:00",
      "movie": "Hamnet",
      "theater": "Downtown Brooklyn",
      "cinema_id": "2101",
      "session_id": "119802",
      "presentation_slug": "hamnet",
      "open_caption": true
    },
    {
      "show_time": "2025-12-07T12:45:00",
      "movie": "Jujutsu Kaisen: Execution (Subtitled)",
      "theater": "Downtown Brooklyn",
      "cinema_id": "2101",
      "session_id": "118699",
      "presentation_slug": "jujutsu-kaisen-execution-subtitled",
      "open_caption": false
    },
    {
      "show_time": "2025-12-07T13:15:00",
      "movie": "Eternity",
      "theater": "Downtown Brooklyn",
      "cinema_id": "2101",
      "session_id": "119819",
      "presentation_slug": "eternity",
      "open_caption": false
    },
    {
      "show_time": "2025-12-07T13:25:00",
      "movie": "Eternity",
      "theater": "Lower Manhattan",
      "cinema_id": "2103",
      "session_id": "81322",
      "presentation_slug": "eternity",
      "open_caption": false
    },
    {
      "show_time": "2025-12-07T13:30:00",
      "movie": "Five Nights at Freddy's 2",
      "theater": "Lower Manhattan",
      "cinema_id": "2103",
      "session_id": "79451",
      "presentation_slug": "five-nights-at-freddys-2",
      "open_caption": false
    },
    {
      "show_time": "2025-12-07T13:30:00",
      "movie": "Five Nights at Freddy's 2",
      "theater": "Downtown Brooklyn",
      "cinema_id": "2101",
      "session_id": "118052",
      "presentation_slug": "five-nights-at-freddys-2",
      "open_caption": false
    },
    {
      "show_time": "2025-12-07T13:45:00",
      "movie": "Jujutsu Kaisen: Execution (Subtitled)",
      "theater": "Lower Manhattan",
      "cinema_id": "2103",
      "session_id": "79823",
      "presentation_slug": "jujutsu-kaisen-execution-subtitled",
      "open_caption": false
    },
    {
      "show_time": "2025-12-07T13:45:00",
      "movie": "The Running Man (2025)",
      "theater": "Downtown Brooklyn",
      "cinema_id": "2101",
      "session_id": "119814",
      "presentation_slug": "the-running-man-2025",
      "open_caption": true
    },
    {
      "show_time": "2025-12-07T14:15:00",
      "movie": "Wake Up Dead Man: A Knives Out Mystery",
      "theater": "Downtown Brooklyn",
      "cinema_id": "2101",
      "session_id": "119792",
      "presentation_slug": "wake-up-dead-man-a-knives-out-mystery",
      "open_caption": false
    },
    {
      "show_time": "2025-12-07T14:20:00",
      "movie": "Wicked: For Good",
      "theater": "Lower Manhattan",
      "cinema_id": "2103",
      "session_id": "81534",
      "presentation_slug": "wicked-for-good",
      "open_caption": true
    },
    {
      "show_time": "2025-12-07T14:25:00",
      "movie": "Wake Up Dead Man: A Knives Out Mystery",
      "theater": "Lower Manhattan",
      "cinema_id": "2103",
      "session_id": "81335",
      "presentation_slug": "wake-up-dead-man-a-knives-out-mystery",
      "open_caption": false
    },
    {
      "show_time": "2025-12-07T14:30:00",
      "movie": "Wicked: For Good",
      "theater": "Downtown Brooklyn",
      "cinema_id": "2101",
      "session_id": "119796",
      "presentation_slug": "wicked-for-good",
      "open_caption": false
    },
    {
      "show_time": "2025-12-07T14:45:00",
      "movie": "100 Nights of Hero",
      "theater": "Downtown Brooklyn",
      "cinema_id": "2101",
      "session_id": "119085",
      "presentation_slug": "100-nights-of-hero",
      "open_caption": false
    },
    {
      "show_time": "2025-12-07T14:50:00",
      "movie": "Wicked: For Good",
      "theater": "Lower Manhattan",
      "cinema_id": "2103",
      "session_id": "81339",
      "presentation_slug": "wicked-for-good",
      "open_caption": false
    },
    {
      "show_time": "2025-12-07T14:55:00",
      "movie": "Wake Up Dead Man: A Knives Out Mystery",
      "theater": "Lower Manhattan",
      "cinema_id": "2103",
      "session_id": "81349",
      "presentation_slug": "wake-up-dead-man-a-knives-out-mystery",
      "open_caption": false
    },
    {
      "show_time": "2025-12-07T14:55:00",
      "movie": "Zootopia 2",
      "theater": "Lower Manhattan",
      "cinema_id": "2103",
      "session_id": "81538",
      "presentation_slug": "zootopia-2",
      "open_caption": true
    },
    {
      "show_time": "2025-12-07T15:05:00",
      "movie": "Risky Business",
      "theater": "Lower Manhattan",
      "cinema_id": "2103",
      "session_id": "80622",
      "presentation_slug": "guest-selects-risky-business",
      "open_caption": false
    },
    {
      "show_time": "2025-12-07T15:15:00",
      "movie": "Suburban Fury",
      "theater": "Lower Manhattan",
      "cinema_id": "2103",
      "session_id": "80145",
      "presentation_slug": "suburban-fury",
      "open_caption": false
    },
    {
      "show_time": "2025-12-07T15:15:00",
      "movie": "Zootopia 2",
      "theater": "Downtown Brooklyn",
      "cinema_id": "2101",
      "session_id": "119788",
      "presentation_slug": "zootopia-2",
      "open_caption": false
    },
    {
      "show_time": "2025-12-07T15:20:00",
      "movie": "Wake Up Dead Man: A Knives Out Mystery",
      "theater": "Lower Manhattan",
      "cinema_id": "2103",
      "session_id": "81342",
      "presentation_slug": "wake-up-dead-man-a-knives-out-mystery",
      "open_caption": false
    },
    {
      "show_time": "2025-12-07T15:25:00",
      "movie": "Hamnet",
      "theater": "Lower Manhattan",
      "cinema_id": "2103",
      "session_id": "81318",
      "presentation_slug": "hamnet",
      "open_caption": false
    },
    {
      "show_time": "2025-12-07T15:30:00",
      "movie": "Jujutsu Kaisen: Execution (Dubbed)",
      "theater": "Downtown Brooklyn",
      "cinema_id": "2101",
      "session_id": "118700",
      "presentation_slug": "jujutsu-kaisen-execution-dubbed",
      "open_caption": false
    },
    {
      "show_time": "2025-12-07T15:45:00",
      "movie": "Now You See Me: Now You Don't",
      "theater": "Downtown Brooklyn",
      "cinema_id": "2101",
      "session_id": "119806",
      "presentation_slug": "now-you-see-me-now-you-dont",
      "open_caption": false
    },
    {
      "show_time": "2025-12-07T15:45:00",
      "movie": "Sentimental Value",
      "theater": "Downtown Brooklyn",
      "cinema_id": "2101",
      "session_id": "119781",
      "presentation_slug": "sentimental-value",
      "open_caption": false
    },
    {
      "show_time": "2025-12-07T16:00:00",
      "movie": "Hamnet",
      "theater": "Downtown Brooklyn",
      "cinema_id": "2101",
      "session_id": "119801",
      "presentation_slug": "hamnet",
      "open_caption": false
    },
    {
      "show_time": "2025-12-07T16:00:00",
      "movie": "Wicked: For Good",
      "theater": "Downtown Brooklyn",
      "cinema_id": "2101",
      "session_id": "119810",
      "presentation_slug": "wicked-for-good",
      "open_caption": false
    },
    {
      "show_time": "2025-12-07T16:20:00",
      "movie": "Eternity",
      "theater": "Lower Manhattan",
      "cinema_id": "2103",
      "session_id": "81323",
      "presentation_slug": "eternity",
      "open_caption": false
    },
    {
      "show_time": "2025-12-07T16:30:00",
      "movie": "Eternity",
      "theater": "Downtown Brooklyn",
      "cinema_id": "2101",
      "session_id": "119817",
      "presentation_slug": "eternity",
      "open_caption": false
    },
    {
      "show_time": "2025-12-07T16:30:00",
      "movie": "Five Nights at Freddy's 2",
      "theater": "Downtown Brooklyn",
      "cinema_id": "2101",
      "session_id": "118053",
      "presentation_slug": "five-nights-at-freddys-2",
      "open_caption": false
    },
    {
      "show_time": "2025-12-07T16:30:00",
      "movie": "Five Nights at Freddy's 2",
      "theater": "Lower Manhattan",
      "cinema_id": "2103",
      "session_id": "79449",
      "presentation_slug": "five-nights-at-freddys-2",
      "open_caption": false
    },
    {
      "show_time": "2025-12-07T16:30:00",
      "movie": "Jujutsu Kaisen: Execution (Dubbed)",
      "theater": "Lower Manhattan",
      "cinema_id": "2103",
      "session_id": "79824",
      "presentation_slug": "jujutsu-kaisen-execution-dubbed",
      "open_caption": false
    },
    {
      "show_time": "2025-12-07T17:10:00",
      "movie": "Wake Up Dead Man: A Knives Out Mystery",
      "theater": "Lower Manhattan",
      "cinema_id": "2103",
      "session_id": "81511",
      "presentation_slug": "wake-up-dead-man-a-knives-out-mystery",
      "open_caption": false
    },
    {
      "show_time": "2025-12-07T17:20:00",
      "movie": "Wicked: For Good",
      "theater": "Downtown Brooklyn",
      "cinema_id": "2101",
      "session_id": "119813",
      "presentation_slug": "wicked-for-good",
      "open_caption": false
    },
    {
      "show_time": "2025-12-07T17:30:00",
      "movie": "Risky Business",
      "theater": "Downtown Brooklyn",
      "cinema_id": "2101",
      "session_id": "119398",
      "presentation_slug": "guest-selects-risky-business-35mm",
      "open_caption": false
    },
    {
      "show_time": "2025-12-07T17:45:00",
      "movie": "Wicked: For Good",
      "theater": "Lower Manhattan",
      "cinema_id": "2103",
      "session_id": "81315",
      "presentation_slug": "wicked-for-good",
      "open_caption": false
    },
    {
      "show_time": "2025-12-07T17:55:00",
      "movie": "Sentimental Value",
      "theater": "Lower Manhattan",
      "cinema_id": "2103",
      "session_id": "81328",
      "presentation_slug": "sentimental-value",
      "open_caption": false
    },
    {
      "show_time": "2025-12-07T18:00:00",
      "movie": "Wicked: For Good",
      "theater": "Downtown Brooklyn",
      "cinema_id": "2101",
      "session_id": "119797",
      "presentation_slug": "wicked-for-good",
      "open_caption": false
    },
    {
      "show_time": "2025-12-07T18:00:00",
      "movie": "Zootopia 2",
      "theater": "Lower Manhattan",
      "cinema_id": "2103",
      "session_id": "81332",
      "presentation_slug": "zootopia-2",
      "open_caption": false
    }
  ]
}
